pythu/__init__.py
PythU-0.1.dev0.dist-info/LICENSE
PythU-0.1.dev0.dist-info/METADATA
PythU-0.1.dev0.dist-info/WHEEL
PythU-0.1.dev0.dist-info/top_level.txt
PythU-0.1.dev0.dist-info/RECORD
