Metadata-Version: 2.1
Name: PythU
Version: 0.1.dev0
License: # PythU 
License-File: LICENSE
